pyvelociraptor/__init__.py
pyvelociraptor/api_pb2.py
pyvelociraptor/api_pb2_grpc.py
pyvelociraptor/client_example.py
pyvelociraptor/fetch.py
pyvelociraptor/fetch_flow_uploads.py
pyvelociraptor/push_event.py
pyvelociraptor/velo_pandas.py
pyvelociraptor/wrappers.py
pyvelociraptor-0.1.11.dist-info/LICENSE
pyvelociraptor-0.1.11.dist-info/METADATA
pyvelociraptor-0.1.11.dist-info/WHEEL
pyvelociraptor-0.1.11.dist-info/entry_points.txt
pyvelociraptor-0.1.11.dist-info/top_level.txt
pyvelociraptor-0.1.11.dist-info/RECORD
