Metadata-Version: 2.1
Name: pyvelociraptor
Version: 0.1.11
Summary: PyVelociraptor is the python binding for the Velociraptor API
Home-page: https://github.com/Velocidex/pyvelociraptor
Author: The Velociraptor Team
Author-email: support@velocidex.com
License: MIT
Platform: UNKNOWN
Classifier: Development Status :: 4 - Beta
Classifier: Environment :: Console
Classifier: Operating System :: OS Independent
Classifier: Programming Language :: Python
License-File: LICENSE
Requires-Dist: cryptography (==45.0.4)
Requires-Dist: grpcio-tools (==1.73.0)
Requires-Dist: grpcio (==1.73.0)
Requires-Dist: pyyaml (==6.0.2)
